CHANGELOG.rst
MANIFEST.in
README.rst
setup.cfg
setup.py
src/ssdeep/__about__.py
src/ssdeep/__init__.py
src/ssdeep/binding.py
src/ssdeep-lib/AUTHORS
src/ssdeep-lib/COPYING
src/ssdeep-lib/ChangeLog
src/ssdeep-lib/FILEFORMAT
src/ssdeep-lib/INSTALL
src/ssdeep-lib/Makefile.am
src/ssdeep-lib/Makefile.in
src/ssdeep-lib/NEWS
src/ssdeep-lib/README
src/ssdeep-lib/TODO
src/ssdeep-lib/aclocal.m4
src/ssdeep-lib/compile
src/ssdeep-lib/config.guess
src/ssdeep-lib/config.h
src/ssdeep-lib/config.h.in
src/ssdeep-lib/config.sub
src/ssdeep-lib/configure
src/ssdeep-lib/configure.ac
src/ssdeep-lib/cycles.cpp
src/ssdeep-lib/depcomp
src/ssdeep-lib/dig.cpp
src/ssdeep-lib/edit_dist.c
src/ssdeep-lib/edit_dist.h
src/ssdeep-lib/engine.cpp
src/ssdeep-lib/filedata.cpp
src/ssdeep-lib/filedata.h
src/ssdeep-lib/find-file-size.c
src/ssdeep-lib/fuzzy.c
src/ssdeep-lib/fuzzy.h
src/ssdeep-lib/helpers.cpp
src/ssdeep-lib/install-sh
src/ssdeep-lib/ltmain.sh
src/ssdeep-lib/main.cpp
src/ssdeep-lib/main.h
src/ssdeep-lib/match.cpp
src/ssdeep-lib/match.h
src/ssdeep-lib/missing
src/ssdeep-lib/sample.c
src/ssdeep-lib/ssdeep.1
src/ssdeep-lib/ssdeep.h
src/ssdeep-lib/sum_table.h
src/ssdeep-lib/tchar-local.h
src/ssdeep-lib/ui.cpp
src/ssdeep-lib/m4/README
src/ssdeep.egg-info/PKG-INFO
src/ssdeep.egg-info/SOURCES.txt
src/ssdeep.egg-info/dependency_links.txt
src/ssdeep.egg-info/not-zip-safe
src/ssdeep.egg-info/requires.txt
src/ssdeep.egg-info/top_level.txt
src/ssdeep/__pycache__/_ssdeep_cffi_a52cfb2dx627c7d55.c
tests/__init__.py
tests/test_lib.py